vtkapi_mcp/__init__.py
vtkapi_mcp/__main__.py
vtkapi_mcp/core/__init__.py
vtkapi_mcp/core/api_index.py
vtkapi_mcp/server/__init__.py
vtkapi_mcp/server/mcp_server.py
vtkapi_mcp/server/tools.py
vtkapi_mcp/utils/__init__.py
vtkapi_mcp/utils/extraction.py
vtkapi_mcp/utils/search.py
vtkapi_mcp/validation/__init__.py
vtkapi_mcp/validation/class_validator.py
vtkapi_mcp/validation/import_validator.py
vtkapi_mcp/validation/method_validator.py
vtkapi_mcp/validation/models.py
vtkapi_mcp/validation/validator.py
vtkapi_mcp-1.4.0.dist-info/licenses/LICENSE
vtkapi_mcp-1.4.0.dist-info/METADATA
vtkapi_mcp-1.4.0.dist-info/WHEEL
vtkapi_mcp-1.4.0.dist-info/entry_points.txt
vtkapi_mcp-1.4.0.dist-info/top_level.txt
vtkapi_mcp-1.4.0.dist-info/RECORD
