Metadata-Version: 2.4
Name: vtkapi-mcp
Version: 1.4.0
Summary: VTK API validation utilities and MCP server tooling
Author: Patrick O'Leary
License: MIT License
Project-URL: Homepage, https://github.com/patrickoleary/vtkapi-mcp
Project-URL: Bug Tracker, https://github.com/patrickoleary/vtkapi-mcp/issues
Keywords: vtk,validation,mcp,api,llm
Classifier: Development Status :: 5 - Production/Stable
Classifier: Intended Audience :: Developers
Classifier: Topic :: Software Development :: Testing
Classifier: Topic :: Software Development :: Libraries
Classifier: Framework :: AsyncIO
Classifier: Programming Language :: Python :: 3
Classifier: Programming Language :: Python :: 3.10
Classifier: Programming Language :: Python :: 3.11
Classifier: Programming Language :: Python :: 3.12
Classifier: Operating System :: OS Independent
Requires-Python: >=3.10
License-File: LICENSE
Requires-Dist: mcp==1.24.0
Provides-Extra: dev
Requires-Dist: pytest>=8.0.0; extra == "dev"
Requires-Dist: pytest-cov>=4.1.0; extra == "dev"
Requires-Dist: pytest-asyncio>=0.23.0; extra == "dev"
Requires-Dist: ruff>=0.8.0; extra == "dev"
Dynamic: license-file
